django_silk-5.4.1.dist-info/licenses/LICENSE
silk/__init__.py
silk/apps.py
silk/auth.py
silk/collector.py
silk/config.py
silk/errors.py
silk/middleware.py
silk/model_factory.py
silk/models.py
silk/request_filters.py
silk/singleton.py
silk/sql.py
silk/storage.py
silk/urls.py
silk/code_generation/__init__.py
silk/code_generation/curl.py
silk/code_generation/django_test_client.py
silk/management/__init__.py
silk/management/commands/__init__.py
silk/management/commands/silk_clear_request_log.py
silk/management/commands/silk_request_garbage_collect.py
silk/migrations/0001_initial.py
silk/migrations/0002_auto_update_uuid4_id_field.py
silk/migrations/0003_request_prof_file.py
silk/migrations/0004_request_prof_file_storage.py
silk/migrations/0005_increase_request_prof_file_length.py
silk/migrations/0006_fix_request_prof_file_blank.py
silk/migrations/0007_sqlquery_identifier.py
silk/migrations/0008_sqlquery_analysis.py
silk/migrations/__init__.py
silk/profiling/__init__.py
silk/profiling/dynamic.py
silk/profiling/profiler.py
silk/static/silk/favicon-16x16.png
silk/static/silk/favicon-32x32.png
silk/static/silk/filter.png
silk/static/silk/filter2.png
silk/static/silk/css/components/cell.css
silk/static/silk/css/components/colors.css
silk/static/silk/css/components/fonts.css
silk/static/silk/css/components/heading.css
silk/static/silk/css/components/numeric.css
silk/static/silk/css/components/row.css
silk/static/silk/css/components/summary.css
silk/static/silk/css/pages/base.css
silk/static/silk/css/pages/clear_db.css
silk/static/silk/css/pages/cprofile.css
silk/static/silk/css/pages/detail_base.css
silk/static/silk/css/pages/profile_detail.css
silk/static/silk/css/pages/profiling.css
silk/static/silk/css/pages/raw.css
silk/static/silk/css/pages/request.css
silk/static/silk/css/pages/requests.css
silk/static/silk/css/pages/root_base.css
silk/static/silk/css/pages/sql.css
silk/static/silk/css/pages/sql_detail.css
silk/static/silk/css/pages/summary.css
silk/static/silk/fonts/glyphicons-halflings-regular.eot
django_silk-5.4.1.dist-info/METADATA
django_silk-5.4.1.dist-info/WHEEL
django_silk-5.4.1.dist-info/top_level.txt
django_silk-5.4.1.dist-info/RECORD
